yxspkg_pip.py
yxspkg_pip-1.1.dist-info/METADATA
yxspkg_pip-1.1.dist-info/WHEEL
yxspkg_pip-1.1.dist-info/top_level.txt
yxspkg_pip-1.1.dist-info/RECORD
